MANIFEST.in
README.md
setup.py
cmd/djangoforandroid
cmd/djangoforandroid.py
djangoforandroid/.directory
djangoforandroid/__init__.py
djangoforandroid.egg-info/PKG-INFO
djangoforandroid.egg-info/SOURCES.txt
djangoforandroid.egg-info/dependency_links.txt
djangoforandroid.egg-info/requires.txt
djangoforandroid.egg-info/top_level.txt
djangoforandroid/builder/__init__.py
djangoforandroid/builder/management/__init__.py
djangoforandroid/builder/management/commands/__init__.py
djangoforandroid/builder/management/commands/_settings.py
djangoforandroid/builder/management/commands/_tools.py
djangoforandroid/builder/management/commands/androidapk.py
djangoforandroid/builder/management/commands/androidcreate.py
djangoforandroid/builder/management/commands/androidgenkey.py
djangoforandroid/builder/management/commands/androidrunserver.py
djangoforandroid/core/__init__.py
djangoforandroid/core/archs.py
djangoforandroid/core/bdistapk.py
djangoforandroid/core/bootstrap.py
djangoforandroid/core/build.py
djangoforandroid/core/distribution.py
djangoforandroid/core/graph.py
djangoforandroid/core/logger.py
djangoforandroid/core/patching.py
djangoforandroid/core/recipe.py
djangoforandroid/core/toolchain.py
djangoforandroid/core/util.py
djangoforandroid/core/bootstraps/__init__.py
djangoforandroid/core/bootstraps/webview/__init__.py
djangoforandroid/core/bootstraps/webview/build/ant.properties
djangoforandroid/core/bootstraps/webview/build/blacklist.txt
djangoforandroid/core/bootstraps/webview/build/build.properties
djangoforandroid/core/bootstraps/webview/build/build.py
djangoforandroid/core/bootstraps/webview/build/build.xml
djangoforandroid/core/bootstraps/webview/build/proguard-project.txt
djangoforandroid/core/bootstraps/webview/build/whitelist.txt
djangoforandroid/core/bootstraps/webview/build/jni/Android.mk
djangoforandroid/core/bootstraps/webview/build/jni/Application.mk
djangoforandroid/core/bootstraps/webview/build/jni/src/Android.mk
djangoforandroid/core/bootstraps/webview/build/jni/src/Android_static.mk
djangoforandroid/core/bootstraps/webview/build/jni/src/pyjniusjni.c
djangoforandroid/core/bootstraps/webview/build/jni/src/start.c
