Metadata-Version: 1.1
Name: djangoforandroid
Version: 2.18
Summary: Deploy Django web application on Android as APK.
Home-page: http://yeisoncardona.com/
Author: Yeison Cardona
Author-email: yeisoneng@gmail.com
License: BSD License
Download-URL: https://bitbucket.org/djangoforandroid/django-for-android/downloads
Platform: UNKNOWN
Classifier: Environment :: Web Environment
Classifier: Framework :: Django
